topsis/__init__.py
topsis/topsis.py
topsis_kashvi_102303564-1.0.0.dist-info/licenses/LICENSE
topsis_kashvi_102303564-1.0.0.dist-info/METADATA
topsis_kashvi_102303564-1.0.0.dist-info/WHEEL
topsis_kashvi_102303564-1.0.0.dist-info/entry_points.txt
topsis_kashvi_102303564-1.0.0.dist-info/top_level.txt
topsis_kashvi_102303564-1.0.0.dist-info/RECORD
