Metadata-Version: 2.4
Name: topsis_kashvi_102303564
Version: 1.0.0
Summary: TOPSIS implementation in Python (Command Line Tool)
Author: Kashvi Aggarwal
Author-email: kaggarwal_be23@thapar.edu
Requires-Python: >=3.7
License-File: LICENSE
Requires-Dist: numpy
Requires-Dist: pandas
Dynamic: author
Dynamic: author-email
Dynamic: description
Dynamic: description-content-type
Dynamic: license-file
Dynamic: requires-dist
Dynamic: requires-python
Dynamic: summary
